AUTHORS
CHANGELOG.txt
DESCRIPTION
LICENSE
MANIFEST.in
README.rst
requirements.txt
setup.cfg
setup.py
tox.ini
django_server_guardian.egg-info/PKG-INFO
django_server_guardian.egg-info/SOURCES.txt
django_server_guardian.egg-info/dependency_links.txt
django_server_guardian.egg-info/requires.txt
django_server_guardian.egg-info/top_level.txt
server_guardian/__init__.py
server_guardian/admin.py
server_guardian/constants.py
server_guardian/default_settings.py
server_guardian/models.py
server_guardian/urls.py
server_guardian/views.py
server_guardian/management/__init__.py
server_guardian/management/commands/__init__.py
server_guardian/management/commands/guardian_fetch.py
server_guardian/migrations/0001_initial.py
server_guardian/migrations/0002_auto_20160222_0336.py
server_guardian/migrations/0003_auto_20160222_0343.py
server_guardian/migrations/0004_remove_server_logging.py
server_guardian/migrations/0005_auto_20160222_0420.py
server_guardian/migrations/0006_remove_serverlog_response_body.py
server_guardian/migrations/__init__.py
server_guardian/static/server_guardian/css/styles.css
server_guardian/templates/server_guardian/server_list.html
server_guardian/templates/server_guardian/email/email_subject.html
server_guardian/templates/server_guardian/email/warning_email_body.html
server_guardian/tests/__init__.py
server_guardian/tests/guardian_fetch_tests.py
server_guardian/tests/mixes.py
server_guardian/tests/models_tests.py
server_guardian/tests/settings.py
server_guardian/tests/test_settings.py
server_guardian/tests/urls.py
server_guardian/tests/views_tests.py
server_guardian/tests/test_app/__init__.py
server_guardian/tests/test_app/models.py
server_guardian/tests/test_app/templates/400.html
server_guardian/tests/test_app/templates/500.html
server_guardian/tests/test_app/templates/base.html