Metadata-Version: 1.0
Name: django-server-guardian
Version: 0.3.2
Summary: A reusable Django app, that fetches and visualizes server health metrics.
